urchin/__init__.py
urchin/urdf.py
urchin/utils.py
urchin/version.py
urchin-0.0.29.dist-info/LICENSE
urchin-0.0.29.dist-info/METADATA
urchin-0.0.29.dist-info/WHEEL
urchin-0.0.29.dist-info/top_level.txt
urchin-0.0.29.dist-info/RECORD
